fifo_with_spram/rtl/DO_mux.v
`define WIDTH 3
`define DATA_WIDTH 8

module DO_mux (
    input clk,
    input rd_en,
    input en0,
    input en1,
    input [`DATA_WIDTH-1:0] data0,
    input [`DATA_WIDTH-1:0] data1,
   
    output [`DATA_WIDTH-1:0] out,
    output read_valid
);
    reg en0_r;
    reg en1_r;
    assign out = (en0) ? data0 : (en1) ? data1 : 32'hffffffff;
    assign read_valid = (en0 | en1);
    

endmodule

fifo_with_spram/rtl/single_port_ram.v
`define WIDTH 3
`define DATA_WIDTH 8

module single_port_ram (
    input clk,
    input rst,
    input ena,
    input wea,
    input [`DATA_WIDTH-1:0] din,
    input [`WIDTH-2:0] addr,
    output reg [`DATA_WIDTH-1:0] dout,
    output reg read_valid
);
    parameter num = 1 << `WIDTH;
    reg [`DATA_WIDTH-1:0] ram[num-1:0];
    
    always @(posedge clk) begin
        if (rst) begin
            for (int i = 0; i < num; i = i + 1) begin
                ram[i] = 0;
            end
            dout <= 0;
            read_valid <= 1'b0;
        end else if (ena && wea) begin
            ram[addr]  <= din;
            read_valid <= 1'b0;
        end else if (ena && ~wea) begin
            dout <= ram[addr];
            read_valid <= 1'b1;
        end else read_valid <= 1'b0;
    end


endmodule

fifo_with_spram/rtl/mem_ctr.v
`define WIDTH 3
`define DATA_WIDTH 8

module mem_ctr (
    input clk,
    input rst,
    input WE_N,
    input RE_N,
    input [`WIDTH-1:0] R_ADR,
    input [`WIDTH-1:0] W_ADR,
    input [`DATA_WIDTH-1:0] DI,
    //----------single port ram_0 signal----------//
    output ENABLE_0,
    output WE_0,
    output [`WIDTH-2:0] A_0,
    output [`DATA_WIDTH-1:0] DI_0,
    //----------single port ram_0 signal----------//
    output ENABLE_1,
    output WE_1,
    output [`WIDTH-2:0] A_1,
    output [`DATA_WIDTH-1:0] DI_1
);
    wire R_bit, W_bit;
    wire [`WIDTH-2:0] R_A;
    wire [`WIDTH-2:0] W_A;
    wire CONFLICT;

    //--- write signal  register --------//
    reg W_bit_D;
    reg [`WIDTH-2:0] W_A_D;
    reg [`DATA_WIDTH-1:0] DI_D;
    reg flag;
    //----------------------------------//
    assign {R_A, R_bit} = R_ADR;
    assign {W_A, W_bit} = W_ADR;

    //----------  read & write conflct check--------//
    assign CONFLICT = (RE_N & WE_N) && (R_bit ^~ W_bit) ? 1'b1 : 1'b0;
    // if conflict ,use reg to  keep write signal for 1 clk 

    always @(posedge clk) begin
        if (rst) begin

            W_bit_D <= 1'b0;
            W_A_D <= 0;
            DI_D <= 0;
            flag <= 1'b0;
        end else if (CONFLICT) begin
            W_bit_D <= W_bit ;
            W_A_D <= W_A   ;
            DI_D <= DI  ;
            flag <= 1'b1 ;
        end else begin
            flag <= 1'b0;

        end

    end





    assign ENABLE_0 = (RE_N & ~R_bit) | (WE_N & ~W_bit) | (flag & ~W_bit_D);
    assign ENABLE_1 = (RE_N & R_bit) | (WE_N & W_bit) | (flag & W_bit_D);

    assign WE_0 = (~(RE_N & ~R_bit)) & (WE_N & ~W_bit) | (flag & ~W_bit_D);
    assign WE_1 = (~(RE_N & R_bit)) & (WE_N & W_bit) | (flag & W_bit_D);


    assign A_0 = (RE_N & ~R_bit) ? R_A : (flag & ~W_bit_D) ? W_A_D : (WE_N & ~W_bit) ? W_A : R_A;

    assign A_1 = (RE_N & R_bit) ? R_A : (flag & W_bit_D) ? W_A_D : (WE_N & W_bit) ? W_A : R_A;

    assign DI_0 = (flag & ~W_bit_D) ? DI_D : (WE_N & ~W_bit) ? DI : DI_D;

    assign DI_1 = (flag & W_bit_D) ? DI_D : (WE_N & W_bit) ? DI : DI_D;





endmodule

fifo_with_spram/rtl/address_update.v
`define WIDTH 3
`define DATA_WIDTH 8


module address_update (
    input clk,
    input rst,
    input re,
    input we,
    output empty,
    output full,
    output [`WIDTH-1:0] r_adr,
    output [`WIDTH-1:0] w_adr
);


    reg [`WIDTH:0] rd_addr;
    reg [`WIDTH:0] wr_addr;
    assign  full  = (rd_addr[`WIDTH] ^ wr_addr[`WIDTH]) & (rd_addr[`WIDTH-1:0]==wr_addr[`WIDTH-1:0]);
    assign empty = (rd_addr == wr_addr);

    always @(posedge clk) begin
        if (rst) begin
            rd_addr <= 0;

        end else if (re & ~empty) begin
            rd_addr <= rd_addr + 1'b1;

        end

    end


    always @(posedge clk) begin
        if (rst) begin
            wr_addr <= 0;

        end else if ((we & ~full) | (we & re & full)) begin
            wr_addr <= wr_addr + 1'b1;

        end

    end

    assign r_adr = rd_addr[`WIDTH-1:0];
    assign w_adr = wr_addr[`WIDTH-1:0];

endmodule

fifo_with_spram/rtl/request_update.v
`define WIDTH 3
`define DATA_WIDTH 8

module request_update (
    input [`DATA_WIDTH-1:0] di,
    input re,
    input we,
    input clk,
    input rst,
    output we_n,
    output re_n,
    output [`WIDTH-1:0] r_adr,
    output [`WIDTH-1:0] w_adr,
    output r_err,
    output w_err,
    output [`DATA_WIDTH-1:0] data_out
);

    wire full, empty;



    //---------update we_n and re_n--------//
    assign we_n  = (we & (~full) & (~rst)) | (we & re & full);
    assign re_n  = re & (~empty) & (~rst);

    assign w_err = we & (full);
    assign r_err = re & (empty);



    //-----------update r_adr and w_adr---------------//
    address_update lut1 (
        .clk(clk),
        .rst(rst),
        .re(re),
        .we(we),
        .empty(empty),
        .full(full),
        .r_adr(r_adr),
        .w_adr(w_adr)
    );

    assign data_out = di;


endmodule

fifo_with_spram/rtl/fifo_spram.v
`define WIDTH 3
`define DATA_WIDTH 8 

module fifo (
    input [`DATA_WIDTH-1:0] DI,
    input RE,
    input WE,
    input clk,
    input rst,
    output [`DATA_WIDTH-1:0] DO,
    output read_valid,
    output r_err,
    output w_err
);

    wire we_n;
    wire re_n;
    wire [`WIDTH-1:0] r_adr;
    wire [`WIDTH-1:0] w_adr;
    wire [`DATA_WIDTH-1:0] d_out;
    wire read_valid_0, read_valid_1;

    request_update update_addr (
        .di(DI),
        .re(RE),
        .we(WE),
        .clk(clk),
        .rst(rst),
        .we_n(we_n),
        .re_n(re_n),
        .r_adr(r_adr),
        .w_adr(w_adr),
        .r_err(r_err),
        .w_err(w_err),
        .data_out(d_out)
    );

    wire ENABLE_0, ENABLE_1;
    wire WE_0, WE_1;
    wire [`WIDTH-2:0] A_0;
    wire    [`DATA_WIDTH-1:0] DI_0;
    wire [`WIDTH-2:0] A_1;
    wire    [`DATA_WIDTH-1:0] DI_1;
    wire [`DATA_WIDTH-1:0] RAM_0_out, RAM_1_out;

    mem_ctr mem_ctr_1 (
        .clk (clk),
        .rst (rst),
        .WE_N (we_n),
        .RE_N (re_n),
        .R_ADR (r_adr),
        .W_ADR (w_adr),
        .DI  (d_out),
        //----------single port ram_0 signal----------//
        .ENABLE_0 (ENABLE_0),
        .WE_0   (WE_0),
        .A_0   (A_0) ,
        .DI_0   (DI_0),
        //----------single port ram_0 signal----------//
        .ENABLE_1 (ENABLE_1),
        .WE_1   (WE_1),
        .A_1   (A_1),
        .DI_1   (DI_1)
    );

    single_port_ram RAM_0 (
        .clk(clk),
        .rst(rst),
        .ena(ENABLE_0),
        .wea(WE_0),
        .din(DI_0),
        .addr(A_0),
        .dout(RAM_0_out),
        .read_valid(read_valid_0)
    );

    single_port_ram RAM_1 (
        .clk(clk),
        .rst(rst),
        .ena(ENABLE_1),
        .wea(WE_1),
        .din(DI_1),
        .addr(A_1),
        .dout(RAM_1_out),
        .read_valid(read_valid_1)
    );

    DO_mux r (
        .clk(clk),
        .rd_en(RE),
        .en0(read_valid_0),
        .en1(read_valid_1),
        .data0(RAM_0_out),
        .data1(RAM_1_out),
        .out(DO),
        .read_valid(read_valid)
    );

endmodule

fifo_with_spram/sim/instruction.v
`define WIDTH 3
`define DATA_WIDTH 8


module instruction (
    input [`DATA_WIDTH+1:0]    inst,
    input   clk,
    input   rst,
    output  [`DATA_WIDTH-1:0] DO,
    output  read_valid
);
    wire    [`DATA_WIDTH-1:0]  DI;
    wire    RE;
    wire    WE;
    assign DI = inst[`DATA_WIDTH-1:0];
    assign RE = inst[`DATA_WIDTH];
    assign WE = inst[`DATA_WIDTH+1];
    fifo f1 (
        .DI        (DI),
        .RE        (RE),
        .WE        (WE),
        .clk       (clk),
        .rst       (rst),
        .DO        (DO),
        .read_valid(read_valid)
    );


endmodule

fifo_with_spram/sim/sim_tb.v
`define clock_delay(CYCLES) \
for (integer  i = 0; i < CYCLES; i = i + 1) begin \
@(posedge clk); \
end

`define WIDTH 3
`define DATA_WIDTH 8


module top(
   input clk,
   input rstn

    );


     initial begin
        if ($test$plusargs("trace") != 0) begin
            $display("[%0t] Tracing to logs/vlt_dump.vcd...\n", $time);
            $dumpfile("logs/vlt_dump.vcd");
            $dumpvars();
        end
        $display("[%0t] Model running...\n", $time);
    end

    wire rst = !rstn ;
   
   
    reg [`DATA_WIDTH-1:0]  DI;
    reg RE;
    reg WE;
    wire [`DATA_WIDTH-1:0]  DO;
    wire [`DATA_WIDTH+1:0]  inst;
    wire full;
    wire empty;


    reg [`DATA_WIDTH-1:0] verif_data_q[$];
  reg [`DATA_WIDTH-1:0] verif_DI;



   
      initial begin
    WE = 0;
    DI = 0;
    

    for (int iter=0; iter<2; iter++) begin
      for (int i=0; i<32; i++) begin
        @(posedge clk)
         if(!full) begin
        WE = (i%2 == 0)? 1'b1 : 1'b0;
        if (WE) begin
          DI = $urandom;
          verif_data_q.push_front(DI);
        end
      end
      end
    end
  end

  initial begin
    RE = 0;

    

    for (int iter=0; iter<2; iter++) begin
      for (int i=0; i<32; i++) begin
        @(posedge clk)
         if(!empty) begin
        RE = (i%2 == 0)? 1'b0 : 1'b1;
        if (RE) begin
          verif_DI = verif_data_q.pop_back();
          // Check the rdata against modeled wdata
          $display("Checking rdata: expected wdata = %h, rdata = %h", verif_DI, DO);
          assert(DO === verif_DI) else $error("Checking failed: expected wdata = %h, rdata = %h", verif_DI, DO);
        end
      end
      end
    end

    $finish;
  end
    
    

    assign  inst = {WE, RE, DI};    

    wire read_valid;
    instruction ins1(
        .inst(inst),
        .clk (clk),
        .rst (rst),
        .DO (DO),
        .read_valid (read_valid)
    );

endmodule

fifo_with_spram/sim/logs/vlt_dump.vcd
$version Generated by VerilatedVcd $end
$timescale 1ps $end

 $scope module TOP $end
  $var wire  1 R clk $end
  $var wire  1 S rstn $end
  $scope module top $end
   $var wire  8 U DI [7:0] $end
   $var wire  8 , DO [7:0] $end
   $var wire  1 V RE $end
   $var wire  1 W WE $end
   $var wire  1 R clk $end
   $var wire  1 c empty $end
   $var wire  1 b full $end
   $var wire 10 X inst [9:0] $end
   $var wire  1 - read_valid $end
   $var wire  1 T rst $end
   $var wire  1 S rstn $end
   $var wire  8 Y verif_DI [7:0] $end
   $scope module ins1 $end
    $var wire  8 U DI [7:0] $end
    $var wire  8 , DO [7:0] $end
    $var wire  1 V RE $end
    $var wire  1 W WE $end
    $var wire  1 R clk $end
    $var wire 10 X inst [9:0] $end
    $var wire  1 - read_valid $end
    $var wire  1 T rst $end
    $scope module f1 $end
     $var wire  2 ) A_0 [1:0] $end
     $var wire  2 * A_1 [1:0] $end
     $var wire  8 U DI [7:0] $end
     $var wire  8 \ DI_0 [7:0] $end
     $var wire  8 ] DI_1 [7:0] $end
     $var wire  8 , DO [7:0] $end
     $var wire  1 % ENABLE_0 $end
     $var wire  1 & ENABLE_1 $end
     $var wire  8 2 RAM_0_out [7:0] $end
     $var wire  8 3 RAM_1_out [7:0] $end
     $var wire  1 V RE $end
     $var wire  1 W WE $end
     $var wire  1 ' WE_0 $end
     $var wire  1 ( WE_1 $end
     $var wire  1 R clk $end
     $var wire  8 U d_out [7:0] $end
     $var wire  3 . r_adr [2:0] $end
     $var wire  1 Z r_err $end
     $var wire  1 $ re_n $end
     $var wire  1 - read_valid $end
     $var wire  1 0 read_valid_0 $end
     $var wire  1 1 read_valid_1 $end
     $var wire  1 T rst $end
     $var wire  3 / w_adr [2:0] $end
     $var wire  1 [ w_err $end
     $var wire  1 # we_n $end
     $scope module RAM_0 $end
      $var wire  2 ) addr [1:0] $end
      $var wire  1 R clk $end
      $var wire  8 \ din [7:0] $end
      $var wire  8 2 dout [7:0] $end
      $var wire  1 % ena $end
      $var wire 32 d num [31:0] $end
      $var wire  8 4 ram[0] [7:0] $end
      $var wire  8 5 ram[1] [7:0] $end
      $var wire  8 6 ram[2] [7:0] $end
      $var wire  8 7 ram[3] [7:0] $end
      $var wire  8 8 ram[4] [7:0] $end
      $var wire  8 9 ram[5] [7:0] $end
      $var wire  8 : ram[6] [7:0] $end
      $var wire  8 ; ram[7] [7:0] $end
      $var wire  1 0 read_valid $end
      $var wire  1 T rst $end
      $var wire  1 ' wea $end
      $scope module unnamedblk1 $end
       $var wire 32 < i [31:0] $end
      $upscope $end
     $upscope $end
     $scope module RAM_1 $end
      $var wire  2 * addr [1:0] $end
      $var wire  1 R clk $end
      $var wire  8 ] din [7:0] $end
      $var wire  8 3 dout [7:0] $end
      $var wire  1 & ena $end
      $var wire 32 d num [31:0] $end
      $var wire  8 = ram[0] [7:0] $end
      $var wire  8 > ram[1] [7:0] $end
      $var wire  8 ? ram[2] [7:0] $end
      $var wire  8 @ ram[3] [7:0] $end
      $var wire  8 A ram[4] [7:0] $end
      $var wire  8 B ram[5] [7:0] $end
      $var wire  8 C ram[6] [7:0] $end
      $var wire  8 D ram[7] [7:0] $end
      $var wire  1 1 read_valid $end
      $var wire  1 T rst $end
      $var wire  1 ( wea $end
      $scope module unnamedblk1 $end
       $var wire 32 E i [31:0] $end
      $upscope $end
     $upscope $end
     $scope module mem_ctr_1 $end
      $var wire  2 ) A_0 [1:0] $end
      $var wire  2 * A_1 [1:0] $end
      $var wire  1 + CONFLICT $end
      $var wire  8 U DI [7:0] $end
      $var wire  8 \ DI_0 [7:0] $end
      $var wire  8 ] DI_1 [7:0] $end
      $var wire  8 L DI_D [7:0] $end
      $var wire  1 % ENABLE_0 $end
      $var wire  1 & ENABLE_1 $end
      $var wire  1 $ RE_N $end
      $var wire  2 H R_A [1:0] $end
      $var wire  3 . R_ADR [2:0] $end
      $var wire  1 F R_bit $end
      $var wire  1 ' WE_0 $end
      $var wire  1 ( WE_1 $end
      $var wire  1 # WE_N $end
      $var wire  2 I W_A [1:0] $end
      $var wire  3 / W_ADR [2:0] $end
      $var wire  2 K W_A_D [1:0] $end
      $var wire  1 G W_bit $end
      $var wire  1 J W_bit_D $end
      $var wire  1 R clk $end
      $var wire  1 M flag $end
      $var wire  1 T rst $end
     $upscope $end
     $scope module r $end
      $var wire  1 R clk $end
      $var wire  8 2 data0 [7:0] $end
      $var wire  8 3 data1 [7:0] $end
      $var wire  1 0 en0 $end
      $var wire  1 e en0_r $end
      $var wire  1 1 en1 $end
      $var wire  1 f en1_r $end
      $var wire  8 , out [7:0] $end
      $var wire  1 V rd_en $end
      $var wire  1 - read_valid $end
     $upscope $end
     $scope module update_addr $end
      $var wire  1 R clk $end
      $var wire  8 U data_out [7:0] $end
      $var wire  8 U di [7:0] $end
      $var wire  1 O empty $end
      $var wire  1 N full $end
      $var wire  3 . r_adr [2:0] $end
      $var wire  1 Z r_err $end
      $var wire  1 V re $end
      $var wire  1 $ re_n $end
      $var wire  1 T rst $end
      $var wire  3 / w_adr [2:0] $end
      $var wire  1 [ w_err $end
      $var wire  1 W we $end
      $var wire  1 # we_n $end
      $scope module lut1 $end
       $var wire  1 R clk $end
       $var wire  1 O empty $end
       $var wire  1 N full $end
       $var wire  3 . r_adr [2:0] $end
       $var wire  4 P rd_addr [3:0] $end
       $var wire  1 V re $end
       $var wire  1 T rst $end
       $var wire  3 / w_adr [2:0] $end
       $var wire  1 W we $end
       $var wire  4 Q wr_addr [3:0] $end
      $upscope $end
     $upscope $end
    $upscope $end
   $upscope $end
   $scope module unnamedblk1 $end
    $var wire 32 ^ iter [31:0] $end
    $scope module unnamedblk2 $end
     $var wire 32 _ i [31:0] $end
    $upscope $end
   $upscope $end
   $scope module unnamedblk3 $end
    $var wire 32 ` iter [31:0] $end
    $scope module unnamedblk4 $end
     $var wire 32 a i [31:0] $end
    $upscope $end
   $upscope $end
  $upscope $end
 $upscope $end
$enddefinitions $end


#0
0#
0$
0%
0&
0'
0(
b10 )
b10 *
0+
b11110100 ,
1-
b100 .
b110 /
10
11
b11110100 2
b00111011 3
b01100011 4
b11000000 5
b00011101 6
b00100010 7
b00000110 8
b10000001 9
b01100011 :
b01111000 ;
b00000000000000000000000000000000 <
b01101111 =
b11001110 >
b11110111 ?
b11010001 @
b10011110 A
b01110111 B
b01101110 C
b10101000 D
b00000000000000000000000000000000 E
0F
0G
b10 H
b11 I
0J
b10 K
b00010000 L
0M
0N
0O
b1100 P
b1110 Q
0R
0S
1T
b00000000 U
0V
0W
b0000000000 X
b10110111 Y
0Z
0[
b00010000 \
b00010000 ]
b00000000000000000000000000000000 ^
b00000000000000000000000000000000 _
b00000000000000000000000000000000 `
b00000000000000000000000000000000 a
0b
0c
b00000000000000000000000000001000 d
1e
1f
#1
1S
0T
#2
0S
1T
#3
1S
0T
#5
1#
1&
1(
b11 *
b11111111 ,
0-
b111 /
00
01
b11100010 7
1G
b1111 Q
1R
b11100010 U
1W
b1011100010 X
b11100010 ]
b00000000000000000000000000000001 _
b00000000000000000000000000000001 a
#6
0R
#7
0#
1$
0(
b10 *
b00011101 ,
1-
b101 .
10
b00011101 2
1F
b1101 P
1R
1V
0W
b0111100010 X
b11100010 Y
b00010000 ]
b00000000000000000000000000000010 _
b00000000000000000000000000000010 a
#8
0R
#9
1#
0$
1%
0&
1'
b00 )
b11111111 ,
0-
b000 /
00
b01100110 @
0G
b00 I
b0000 Q
1R
b01100110 U
0V
1W
b1001100110 X
b01100110 \
b00000000000000000000000000000011 _
b00000000000000000000000000000011 a
#10
0R
#11
0#
1$
0'
b11 )
b11 *
b11110111 ,
1-
b110 .
11
b11110111 3
0F
b11 H
b1110 P
1R
1V
0W
b0101100110 X
b01100110 Y
b00010000 \
b00000000000000000000000000000100 _
b00000000000000000000000000000100 a
#12
0R
#13
1#
0$
0%
1&
1(
b00 *
b11111111 ,
0-
b001 /
01
b00011111 4
1G
b0001 Q
1R
b00011111 U
0V
1W
b1000011111 X
b00011111 ]
b00000000000000000000000000000101 _
b00000000000000000000000000000101 a
#14
0R
#15
0#
1$
0(
b11 *
b11100010 ,
1-
b111 .
10
b11100010 2
1F
b1111 P
1R
1V
0W
b0100011111 X
b00011111 Y
b00010000 ]
b00000000000000000000000000000110 _
b00000000000000000000000000000110 a
#16
0R
#17
1#
0$
1%
0&
1'
b01 )
b11111111 ,
0-
b010 /
00
b00001001 =
0G
b01 I
b0010 Q
1R
b00001001 U
0V
1W
b1000001001 X
b00001001 \
b00000000000000000000000000000111 _
b00000000000000000000000000000111 a
#18
0R
#19
0#
1$
0'
b00 )
b00 *
b01100110 ,
1-
b000 .
11
b01100110 3
0F
b00 H
b0000 P
1R
1V
0W
b0100001001 X
b00001001 Y
b00010000 \
b00000000000000000000000000001000 _
b00000000000000000000000000001000 a
#20
0R
#21
1#
0$
0%
1&
1(
b01 *
b11111111 ,
0-
b011 /
01
b11100011 5
1G
b0011 Q
1R
b11100011 U
0V
1W
b1011100011 X
b11100011 ]
b00000000000000000000000000001001 _
b00000000000000000000000000001001 a
#22
0R
#23
0#
1$
0(
b00 *
b00011111 ,
1-
b001 .
10
b00011111 2
1F
b0001 P
1R
1V
0W
b0111100011 X
b11100011 Y
b00010000 ]
b00000000000000000000000000001010 _
b00000000000000000000000000001010 a
#24
0R
#25
1#
0$
1%
0&
1'
b10 )
b11111111 ,
0-
b100 /
00
b00011111 >
0G
b10 I
b0100 Q
1R
b00011111 U
0V
1W
b1000011111 X
b00011111 \
b00000000000000000000000000001011 _
b00000000000000000000000000001011 a
#26
0R
#27
0#
1$
0'
b01 )
b01 *
b00001001 ,
1-
b010 .
11
b00001001 3
0F
b01 H
b0010 P
1R
1V
0W
b0100011111 X
b00011111 Y
b00010000 \
b00000000000000000000000000001100 _
b00000000000000000000000000001100 a
#28
0R
#29
1#
0$
0%
1&
1(
b10 *
b11111111 ,
0-
b101 /
01
b10000100 6
1G
b0101 Q
1R
b10000100 U
0V
1W
b1010000100 X
b10000100 ]
b00000000000000000000000000001101 _
b00000000000000000000000000001101 a
#30
0R
#31
0#
1$
0(
b01 *
b11100011 ,
1-
b011 .
10
b11100011 2
1F
b0011 P
1R
1V
0W
b0110000100 X
b10000100 Y
b00010000 ]
b00000000000000000000000000001110 _
b00000000000000000000000000001110 a
#32
0R
#33
1#
0$
1%
0&
1'
b11 )
b11111111 ,
0-
b110 /
00
b11000101 ?
0G
b11 I
b0110 Q
1R
b11000101 U
0V
1W
b1011000101 X
b11000101 \
b00000000000000000000000000001111 _
b00000000000000000000000000001111 a
#34
0R
#35
0#
1$
0'
b10 )
b10 *
b00011111 ,
1-
b100 .
11
b00011111 3
0F
b10 H
b0100 P
1R
1V
0W
b0111000101 X
b11000101 Y
b00010000 \
b00000000000000000000000000010000 _
b00000000000000000000000000010000 a
#36
0R
#37
1#
0$
0%
1&
1(
b11 *
b11111111 ,
0-
b111 /
01
b00110011 7
1G
b0111 Q
1R
b00110011 U
0V
1W
b1000110011 X
b00110011 ]
b00000000000000000000000000010001 _
b00000000000000000000000000010001 a
#38
0R
#39
0#
1$
0(
b10 *
b10000100 ,
1-
b101 .
10
b10000100 2
1F
b0101 P
1R
1V
0W
b0100110011 X
b00110011 Y
b00010000 ]
b00000000000000000000000000010010 _
b00000000000000000000000000010010 a
#40
0R
#41
1#
0$
1%
0&
1'
b00 )
b11111111 ,
0-
b000 /
00
b01001011 @
0G
b00 I
b1000 Q
1R
b01001011 U
0V
1W
b1001001011 X
b01001011 \
b00000000000000000000000000010011 _
b00000000000000000000000000010011 a
#42
0R
#43
0#
1$
0'
b11 )
b11 *
b11000101 ,
1-
b110 .
11
b11000101 3
0F
b11 H
b0110 P
1R
1V
0W
b0101001011 X
b01001011 Y
b00010000 \
b00000000000000000000000000010100 _
b00000000000000000000000000010100 a
#44
0R
#45
1#
0$
0%
1&
1(
b00 *
b11111111 ,
0-
b001 /
01
b10011100 4
1G
b1001 Q
1R
b10011100 U
0V
1W
b1010011100 X
b10011100 ]
b00000000000000000000000000010101 _
b00000000000000000000000000010101 a
#46
0R
#47
0#
1$
0(
b11 *
b00110011 ,
1-
b111 .
10
b00110011 2
1F
b0111 P
1R
1V
0W
b0110011100 X
b10011100 Y
b00010000 ]
b00000000000000000000000000010110 _
b00000000000000000000000000010110 a
#48
0R
#49
1#
0$
1%
0&
1'
b01 )
b11111111 ,
0-
b010 /
00
b11110011 =
0G
b01 I
b1010 Q
1R
b11110011 U
0V
1W
b1011110011 X
b11110011 \
b00000000000000000000000000010111 _
b00000000000000000000000000010111 a
#50
0R
#51
0#
1$
0'
b00 )
b00 *
b01001011 ,
1-
b000 .
11
b01001011 3
0F
b00 H
b1000 P
1R
1V
0W
b0111110011 X
b11110011 Y
b00010000 \
b00000000000000000000000000011000 _
b00000000000000000000000000011000 a
#52
0R
#53
1#
0$
0%
1&
1(
b01 *
b11111111 ,
0-
b011 /
01
b11001001 5
1G
b1011 Q
1R
b11001001 U
0V
1W
b1011001001 X
b11001001 ]
b00000000000000000000000000011001 _
b00000000000000000000000000011001 a
#54
0R
#55
0#
1$
0(
b00 *
b10011100 ,
1-
b001 .
10
b10011100 2
1F
b1001 P
1R
1V
0W
b0111001001 X
b11001001 Y
b00010000 ]
b00000000000000000000000000011010 _
b00000000000000000000000000011010 a
#56
0R
#57
1#
0$
1%
0&
1'
b10 )
b11111111 ,
0-
b100 /
00
b11101101 >
0G
b10 I
b1100 Q
1R
b11101101 U
0V
1W
b1011101101 X
b11101101 \
b00000000000000000000000000011011 _
b00000000000000000000000000011011 a
#58
0R
#59
0#
1$
0'
b01 )
b01 *
b11110011 ,
1-
b010 .
11
b11110011 3
0F
b01 H
b1010 P
1R
1V
0W
b0111101101 X
b11101101 Y
b00010000 \
b00000000000000000000000000011100 _
b00000000000000000000000000011100 a
#60
0R
#61
1#
0$
0%
1&
1(
b10 *
b11111111 ,
0-
b101 /
01
b11001010 6
1G
b1101 Q
1R
b11001010 U
0V
1W
b1011001010 X
b11001010 ]
b00000000000000000000000000011101 _
b00000000000000000000000000011101 a
#62
0R
#63
0#
1$
0(
b01 *
b11001001 ,
1-
b011 .
10
b11001001 2
1F
b1011 P
1R
1V
0W
b0111001010 X
b11001010 Y
b00010000 ]
b00000000000000000000000000011110 _
b00000000000000000000000000011110 a
#64
0R
#65
1#
0$
1%
0&
1'
b11 )
b11111111 ,
0-
b110 /
00
b01011101 ?
0G
b11 I
b1110 Q
1R
b01011101 U
0V
1W
b1001011101 X
b01011101 \
b00000000000000000000000000011111 _
b00000000000000000000000000011111 a
#66
0R
#67
0#
1$
0'
b10 )
b10 *
b11101101 ,
1-
b100 .
11
b11101101 3
0F
b10 H
b1100 P
1R
1V
0W
b0101011101 X
b01011101 Y
b00010000 \
b00000000000000000000000000000001 ^
b00000000000000000000000000100000 _
b00000000000000000000000000000001 `
b00000000000000000000000000100000 a
#68
0R
#69
1#
0$
0%
1&
1(
b11 *
b11111111 ,
0-
b111 /
01
b01000111 7
1G
b1111 Q
1R
b01000111 U
0V
1W
b1001000111 X
b01000111 ]
b00000000000000000000000000000001 _
b00000000000000000000000000000001 a
#70
0R
#71
0#
1$
0(
b10 *
b11001010 ,
1-
b101 .
10
b11001010 2
1F
b1101 P
1R
1V
0W
b0101000111 X
b01000111 Y
b00010000 ]
b00000000000000000000000000000010 _
b00000000000000000000000000000010 a
#72
0R
#73
1#
0$
1%
0&
1'
b00 )
b11111111 ,
0-
b000 /
00
b00100100 @
0G
b00 I
b0000 Q
1R
b00100100 U
0V
1W
b1000100100 X
b00100100 \
b00000000000000000000000000000011 _
b00000000000000000000000000000011 a
#74
0R
#75
0#
1$
0'
b11 )
b11 *
b01011101 ,
1-
b110 .
11
b01011101 3
0F
b11 H
b1110 P
1R
1V
0W
b0100100100 X
b00100100 Y
b00010000 \
b00000000000000000000000000000100 _
b00000000000000000000000000000100 a
#76
0R
#77
1#
0$
0%
1&
1(
b00 *
b11111111 ,
0-
b001 /
01
b11101111 4
1G
b0001 Q
1R
b11101111 U
0V
1W
b1011101111 X
b11101111 ]
b00000000000000000000000000000101 _
b00000000000000000000000000000101 a
#78
0R
#79
0#
1$
0(
b11 *
b01000111 ,
1-
b111 .
10
b01000111 2
1F
b1111 P
1R
1V
0W
b0111101111 X
b11101111 Y
b00010000 ]
b00000000000000000000000000000110 _
b00000000000000000000000000000110 a
#80
0R
#81
1#
0$
1%
0&
1'
b01 )
b11111111 ,
0-
b010 /
00
b10101001 =
0G
b01 I
b0010 Q
1R
b10101001 U
0V
1W
b1010101001 X
b10101001 \
b00000000000000000000000000000111 _
b00000000000000000000000000000111 a
#82
0R
#83
0#
1$
0'
b00 )
b00 *
b00100100 ,
1-
b000 .
11
b00100100 3
0F
b00 H
b0000 P
1R
1V
0W
b0110101001 X
b10101001 Y
b00010000 \
b00000000000000000000000000001000 _
b00000000000000000000000000001000 a
#84
0R
#85
1#
0$
0%
1&
1(
b01 *
b11111111 ,
0-
b011 /
01
b01101101 5
1G
b0011 Q
1R
b01101101 U
0V
1W
b1001101101 X
b01101101 ]
b00000000000000000000000000001001 _
b00000000000000000000000000001001 a
#86
0R
#87
0#
1$
0(
b00 *
b11101111 ,
1-
b001 .
10
b11101111 2
1F
b0001 P
1R
1V
0W
b0101101101 X
b01101101 Y
b00010000 ]
b00000000000000000000000000001010 _
b00000000000000000000000000001010 a
#88
0R
#89
1#
0$
1%
0&
1'
b10 )
b11111111 ,
0-
b100 /
00
b00111001 >
0G
b10 I
b0100 Q
1R
b00111001 U
0V
1W
b1000111001 X
b00111001 \
b00000000000000000000000000001011 _
b00000000000000000000000000001011 a
#90
0R
#91
0#
1$
0'
b01 )
b01 *
b10101001 ,
1-
b010 .
11
b10101001 3
0F
b01 H
b0010 P
1R
1V
0W
b0100111001 X
b00111001 Y
b00010000 \
b00000000000000000000000000001100 _
b00000000000000000000000000001100 a
#92
0R
#93
1#
0$
0%
1&
1(
b10 *
b11111111 ,
0-
b101 /
01
b01111000 6
1G
b0101 Q
1R
b01111000 U
0V
1W
b1001111000 X
b01111000 ]
b00000000000000000000000000001101 _
b00000000000000000000000000001101 a
#94
0R
#95
0#
1$
0(
b01 *
b01101101 ,
1-
b011 .
10
b01101101 2
1F
b0011 P
1R
1V
0W
b0101111000 X
b01111000 Y
b00010000 ]
b00000000000000000000000000001110 _
b00000000000000000000000000001110 a
#96
0R
#97
1#
0$
1%
0&
1'
b11 )
b11111111 ,
0-
b110 /
00
b11101010 ?
0G
b11 I
b0110 Q
1R
b11101010 U
0V
1W
b1011101010 X
b11101010 \
b00000000000000000000000000001111 _
b00000000000000000000000000001111 a
#98
0R
#99
0#
1$
0'
b10 )
b10 *
b00111001 ,
1-
b100 .
11
b00111001 3
0F
b10 H
b0100 P
1R
1V
0W
b0111101010 X
b11101010 Y
b00010000 \
b00000000000000000000000000010000 _
b00000000000000000000000000010000 a
#100
0R
#101
1#
0$
0%
1&
1(
b11 *
b11111111 ,
0-
b111 /
01
b11000010 7
1G
b0111 Q
1R
b11000010 U
0V
1W
b1011000010 X
b11000010 ]
b00000000000000000000000000010001 _
b00000000000000000000000000010001 a
#102
0R
#103
0#
1$
0(
b10 *
b01111000 ,
1-
b101 .
10
b01111000 2
1F
b0101 P
1R
1V
0W
b0111000010 X
b11000010 Y
b00010000 ]
b00000000000000000000000000010010 _
b00000000000000000000000000010010 a
#104
0R
