fifo/rtl/dpram.v
module dpram # (
    parameter  DATA_WIDTH = 2,
    parameter  ADDR_WIDTH = 5,
    parameter DEPTH       = 16
) (
    input [ADDR_WIDTH-1:0] wr_addr ,
    input [DATA_WIDTH-1:0] wr_data ,
    input wr_en ,

    input [ADDR_WIDTH-1:0] rd_addr ,
    output reg [DATA_WIDTH-1:0] rd_data ,
    input rd_en ,

    input clk
);

reg [DATA_WIDTH-1:0] mem [(DEPTH -1) :0] ;

always @ ( posedge clk ) begin
    if ( wr_en ) begin
        mem [ wr_addr ] <= wr_data ;
    end
end

always @ ( posedge clk ) begin
    if ( rd_en ) begin
        rd_data <= mem [ rd_addr ] ;
    end
end

endmodule

fifo/rtl/fifo.v

module fifo # (

    parameter ADDR_WIDTH  = 5,
    parameter DATA_WIDTH  = 2,
    parameter DEPTH       = 16
)
(
    input reg [DATA_WIDTH-1:0] data_in,
    input clk,
    rst,
    rd,
    wr,
    output empty,
    full,
    output reg [DATA_WIDTH-1:0] data_out
);

    reg [ADDR_WIDTH-1:0] rd_ptr, wr_ptr;

    assign empty = (wr_ptr == rd_ptr);
   assign full  = (wr_ptr == {~rd_ptr[ADDR_WIDTH-1], rd_ptr[ADDR_WIDTH-2:0]});

    always @(posedge clk or posedge rst) begin
        if (rst) begin
            wr_ptr <= 0;
            rd_ptr <= 0;
        end else begin
            wr_ptr <= ((wr && !full) || (wr && rd)) ? wr_ptr + 1 : wr_ptr;

            rd_ptr <= ((rd && !empty) || (wr && rd)) ? rd_ptr + 1 : rd_ptr;
        end
    end


 dpram dp(

    .wr_addr(wr_ptr),
    .wr_data(data_in),
    .wr_en(wr),
    .rd_addr(rd_ptr),
    .rd_data(data_out),
    .rd_en(rd),
    .clk(clk)

);



endmodule

fifo/sim/fifo_tb.v

module top # (

    parameter ADDR_WIDTH  = 5,
    parameter DATA_WIDTH  = 2,
    parameter DEPTH       = 16

)
(
    input clk ,
    input rstn );

   


    
    initial begin
        if ($test$plusargs("trace") != 0) begin
            $display("[%0t] Tracing to logs/vlt_dump.vcd...\n", $time);
            $dumpfile("logs/vlt_dump.vcd");
            $dumpvars();
        end
        $display("[%0t] Model running...\n", $time);
    end

    
    wire rst = !rstn ;

    reg rd;
    reg wr;
    reg [DATA_WIDTH-1:0] data_in;

    wire empty;
    wire full;
    wire [DATA_WIDTH-1:0] data_out;

     reg [DATA_WIDTH-1:0] verif_data_q[$];
  reg [DATA_WIDTH-1:0] verif_data_in;


    fifo dut (
        .data_in(data_in),
        .clk(clk),
        .rst(rst),
        .rd(rd),
        .wr(wr),
        .empty(empty),
        .full(full),
        .data_out(data_out)
    );

    initial begin
    wr = 0;
    rd = 0;
    data_in = 0;

    for (int iter=0; iter<2; iter++) begin
      for (int i=0; i<32; i++) begin
        @(posedge clk)

         if (!full) begin
        wr = (i%2 == 0)? 1'b1 : 1'b0;
        if (wr) begin
          data_in = $urandom;
          verif_data_q.push_front(data_in);
        end
      end
      if(full) begin
        wr = 0;
      end


      if(!empty) begin
        rd = (i%8 == 0) ? 1 : 0;
        if (rd) begin
            verif_data_in = verif_data_q.pop_back();
            $display("Checking rdata: expected wdata = %h, rdata = %h", verif_data_in, data_out);
          assert(data_out === verif_data_in) else $error("Checking failed: expected wdata = %h, rdata = %h", verif_data_in, data_out);

        end

      end
    end
  end

  

    $finish;
  end

endmodule

fifo/sim/logs/vlt_dump.vcd
$version Generated by VerilatedVcd $end
$timescale 1ps $end

 $scope module TOP $end
  $var wire  1 > clk $end
  $var wire  1 ? rstn $end
  $scope module top $end
   $var wire 32 A ADDR_WIDTH [31:0] $end
   $var wire 32 B DATA_WIDTH [31:0] $end
   $var wire 32 C DEPTH [31:0] $end
   $var wire  1 > clk $end
   $var wire  2 % data_in [1:0] $end
   $var wire  2 ) data_out [1:0] $end
   $var wire  1 : empty $end
   $var wire  1 ; full $end
   $var wire  1 # rd $end
   $var wire  1 @ rst $end
   $var wire  1 ? rstn $end
   $var wire  2 & verif_data_in [1:0] $end
   $var wire  1 $ wr $end
   $scope module dut $end
    $var wire 32 A ADDR_WIDTH [31:0] $end
    $var wire 32 B DATA_WIDTH [31:0] $end
    $var wire 32 C DEPTH [31:0] $end
    $var wire  1 > clk $end
    $var wire  2 % data_in [1:0] $end
    $var wire  2 ) data_out [1:0] $end
    $var wire  1 : empty $end
    $var wire  1 ; full $end
    $var wire  1 # rd $end
    $var wire  5 < rd_ptr [4:0] $end
    $var wire  1 @ rst $end
    $var wire  1 $ wr $end
    $var wire  5 = wr_ptr [4:0] $end
    $scope module dp $end
     $var wire 32 A ADDR_WIDTH [31:0] $end
     $var wire 32 B DATA_WIDTH [31:0] $end
     $var wire 32 C DEPTH [31:0] $end
     $var wire  1 > clk $end
     $var wire  2 * mem[0] [1:0] $end
     $var wire  2 4 mem[10] [1:0] $end
     $var wire  2 5 mem[11] [1:0] $end
     $var wire  2 6 mem[12] [1:0] $end
     $var wire  2 7 mem[13] [1:0] $end
     $var wire  2 8 mem[14] [1:0] $end
     $var wire  2 9 mem[15] [1:0] $end
     $var wire  2 + mem[1] [1:0] $end
     $var wire  2 , mem[2] [1:0] $end
     $var wire  2 - mem[3] [1:0] $end
     $var wire  2 . mem[4] [1:0] $end
     $var wire  2 / mem[5] [1:0] $end
     $var wire  2 0 mem[6] [1:0] $end
     $var wire  2 1 mem[7] [1:0] $end
     $var wire  2 2 mem[8] [1:0] $end
     $var wire  2 3 mem[9] [1:0] $end
     $var wire  5 < rd_addr [4:0] $end
     $var wire  2 ) rd_data [1:0] $end
     $var wire  1 # rd_en $end
     $var wire  5 = wr_addr [4:0] $end
     $var wire  2 % wr_data [1:0] $end
     $var wire  1 $ wr_en $end
    $upscope $end
   $upscope $end
   $scope module unnamedblk1 $end
    $var wire 32 ' iter [31:0] $end
    $scope module unnamedblk2 $end
     $var wire 32 ( i [31:0] $end
    $upscope $end
   $upscope $end
  $upscope $end
 $upscope $end
$enddefinitions $end


#0
0#
0$
b00 %
b01 &
b00000000000000000000000000000000 '
b00000000000000000000000000000000 (
b11 )
b10 *
b10 +
b01 ,
b10 -
b10 .
b01 /
b00 0
b11 1
b00 2
b10 3
b00 4
b10 5
b10 6
b10 7
b10 8
b00 9
1:
0;
b00000 <
b00000 =
0>
0?
1@
b00000000000000000000000000000101 A
b00000000000000000000000000000010 B
b00000000000000000000000000010000 C
#1
1?
0@
#2
0?
1@
#3
1?
0@
#5
1$
b00000000000000000000000000000001 (
b00 *
0:
b00001 =
1>
#6
0>
#7
0$
b00000000000000000000000000000010 (
1>
#8
0>
#9
1$
b01 %
b00000000000000000000000000000011 (
b01 +
b00010 =
1>
#10
0>
#11
0$
b00000000000000000000000000000100 (
1>
#12
0>
#13
1$
b10 %
b00000000000000000000000000000101 (
b10 ,
b00011 =
1>
#14
0>
#15
0$
b00000000000000000000000000000110 (
1>
#16
0>
#17
1$
b00000000000000000000000000000111 (
b00100 =
1>
#18
0>
#19
0$
b00000000000000000000000000001000 (
1>
#20
0>
#21
1#
1$
b01 %
b00 &
b00000000000000000000000000001001 (
b00 )
b01 .
b00001 <
b00101 =
1>
#22
0>
#23
0#
0$
b00000000000000000000000000001010 (
1>
#24
0>
#25
1$
b11 %
b00000000000000000000000000001011 (
b11 /
b00110 =
1>
#26
0>
#27
0$
b00000000000000000000000000001100 (
1>
#28
0>
#29
1$
b00 %
b00000000000000000000000000001101 (
b00111 =
1>
#30
0>
#31
0$
b00000000000000000000000000001110 (
1>
#32
0>
#33
1$
b11 %
b00000000000000000000000000001111 (
b01000 =
1>
#34
0>
#35
0$
b00000000000000000000000000010000 (
1>
#36
0>
#37
1#
1$
b10 %
b01 &
b00000000000000000000000000010001 (
b01 )
b10 2
b00010 <
b01001 =
1>
#38
0>
#39
0#
0$
b00000000000000000000000000010010 (
1>
#40
0>
#41
1$
b11 %
b00000000000000000000000000010011 (
b11 3
b01010 =
1>
#42
0>
#43
0$
b00000000000000000000000000010100 (
1>
#44
0>
#45
1$
b01 %
b00000000000000000000000000010101 (
b01 4
b01011 =
1>
#46
0>
#47
0$
b00000000000000000000000000010110 (
1>
#48
0>
#49
1$
b10 %
b00000000000000000000000000010111 (
b01100 =
1>
#50
0>
#51
0$
b00000000000000000000000000011000 (
1>
#52
0>
#53
1#
1$
b11 %
b10 &
b00000000000000000000000000011001 (
b10 )
b11 6
b00011 <
b01101 =
1>
#54
0>
#55
0#
0$
b00000000000000000000000000011010 (
1>
#56
0>
#57
1$
b10 %
b00000000000000000000000000011011 (
b01110 =
1>
#58
0>
#59
0$
b00000000000000000000000000011100 (
1>
#60
0>
#61
1$
b00 %
b00000000000000000000000000011101 (
b00 8
b01111 =
1>
#62
0>
#63
0$
b00000000000000000000000000011110 (
1>
#64
0>
#65
1$
b11 %
b00000000000000000000000000011111 (
b11 9
b10000 =
1>
#66
0>
#67
0$
b00000000000000000000000000000001 '
b00000000000000000000000000100000 (
1>
#68
0>
#69
1#
1$
b00000000000000000000000000000001 (
b11 *
b00100 <
b10001 =
1>
#70
0>
#71
0#
0$
b00000000000000000000000000000010 (
1>
#72
0>
#73
1$
b00 %
b00000000000000000000000000000011 (
b00 +
b10010 =
1>
#74
0>
#75
0$
b00000000000000000000000000000100 (
1>
#76
0>
#77
1$
b10 %
b00000000000000000000000000000101 (
b10011 =
1>
#78
0>
#79
0$
b00000000000000000000000000000110 (
1>
#80
0>
#81
1$
b00000000000000000000000000000111 (
1;
b10100 =
1>
#82
0>
#83
0$
b00000000000000000000000000001000 (
1>
#84
0>
#85
1#
b01 &
b00000000000000000000000000001001 (
b01 )
0;
b00101 <
1>
#86
0>
#87
0#
b00000000000000000000000000001010 (
1>
#88
0>
#89
1$
b11 %
b00000000000000000000000000001011 (
b11 .
1;
b10101 =
1>
#90
0>
#91
0$
b00000000000000000000000000001100 (
1>
#92
0>
#93
b00000000000000000000000000001101 (
1>
#94
0>
#95
b00000000000000000000000000001110 (
1>
#96
0>
#97
b00000000000000000000000000001111 (
1>
#98
0>
#99
b00000000000000000000000000010000 (
1>
#100
0>
#101
1#
b11 &
b00000000000000000000000000010001 (
b11 )
0;
b00110 <
1>
#102
0>
#103
0#
b00000000000000000000000000010010 (
1>
#104
0>
#105
1$
b01 %
b00000000000000000000000000010011 (
b01 /
1;
b10110 =
1>
#106
0>
#107
0$
b00000000000000000000000000010100 (
1>
#108
0>
#109
b00000000000000000000000000010101 (
1>
#110
0>
#111
b00000000000000000000000000010110 (
1>
#112
0>
#113
b00000000000000000000000000010111 (
1>
#114
0>
#115
b00000000000000000000000000011000 (
1>
#116
0>
#117
1#
b00 &
b00000000000000000000000000011001 (
b00 )
0;
b00111 <
1>
#118
0>
#119
0#
b00000000000000000000000000011010 (
1>
#120
0>
#121
1$
b11 %
b00000000000000000000000000011011 (
b11 0
1;
b10111 =
1>
#122
0>
#123
0$
b00000000000000000000000000011100 (
1>
#124
0>
#125
b00000000000000000000000000011101 (
1>
#126
0>
#127
b00000000000000000000000000011110 (
1>
#128
0>
#129
b00000000000000000000000000011111 (
1>
#130
0>
#131
b00000000000000000000000000000010 '
b00000000000000000000000000100000 (
1>
