asynchronous fifo/dp_dcram.v
module dp_dcram(
	wr_clk,
	addr0 ,
	data0,
	we0,

	rd_clk,
	addr1,
	q1,
	re1
);
parameter DWIDTH = 8;
parameter AWIDTH = 8;


input wr_clk;
input rd_clk;
input [DWIDTH-1:0] data0; 
output [DWIDTH-1:0] q1;
input [AWIDTH-1:0] addr0;
input [AWIDTH-1:0] addr1;
input we0, re1;

reg [DWIDTH-1:0] Mem [0:(1<<AWIDTH)-1];
reg [DWIDTH-1:0] q1;

always @(posedge wr_clk)
  if (we0)
    Mem[addr0] <= data0;

always @(posedge rd_clk)
  if (re1)
    q1 <=  Mem[addr1] ;

endmodule

asynchronous fifo/asynch_fifo.v


module asynch_fifo(
	areset_n, 

	wr_clk, 
 	datain, 
	write,

	rd_clk,
	read, 
	q,

	empty,
	full
);
parameter DWIDTH=8;
parameter AWIDTH=6;


input wr_clk;
input areset_n;
input [DWIDTH-1:0] datain;
input write;

input rd_clk;
input read;
output [DWIDTH-1:0] q;
output full;
output empty;


wire [DWIDTH-1:0] q;
wire [DWIDTH-1:0] data_int;
reg full;
wire empty;
reg [AWIDTH-1:0] wptr, rptr;
reg [AWIDTH-1:0] wptr_ms, wptr_rd;
reg [AWIDTH-1:0] rptr_ms, rptr_wr;
reg [AWIDTH:0] wptr_next, rptr_wr_bin;
reg [AWIDTH-1:0] rptr_gray, wptr_gray;
reg [AWIDTH:0] full;
integer i;

reg areset_n_ms, areset_n_wr;

always @(posedge wr_clk ) begin
	areset_n_ms <= areset_n;
	areset_n_wr <= areset_n_ms;
end


always @(posedge wr_clk or negedge areset_n_wr) begin
	if (!areset_n_wr) begin
		wptr <=  {AWIDTH{1'b0}};
	end else if (write) begin
		wptr <=  wptr+1;
	end
end
assign wptr_gray = (wptr >>1) ^ wptr;
assign wptr_next = wptr+1;


always @(posedge wr_clk ) begin
	rptr_ms <= rptr_gray;
	rptr_wr <= rptr_ms;
end

always@(*)
   for (i=0; i<AWIDTH; i = i+1) begin
     rptr_wr_bin[i] = ^(rptr_wr >> i);
   end


assign full  = (wptr_next == rptr_wr_bin);







always @(posedge rd_clk ) begin
	wptr_ms <= wptr_gray;
	wptr_rd <= wptr_ms;
end






always @(posedge rd_clk or negedge areset_n_wr) begin
	if (!areset_n_wr) begin
		rptr <=  {AWIDTH{1'b0}};
	end else if (read) begin
		rptr <=  rptr+1;;
	end
end



assign rptr_gray = (rptr>>1) ^ rptr;

assign q = data_int;


assign	empty = (rptr_gray == wptr_rd);



dp_dcram #(DWIDTH, AWIDTH) dp_dcram_0(
	
	.wr_clk(wr_clk),
	.addr0(wptr),
	.data0(datain),
	.we0(write),
	
	
	.rd_clk(rd_clk),
	.addr1(rptr),
	.q1(data_int),
	.re1(read)
);

endmodule

asynchronous fifo/waveform.vcd
$version Generated by VerilatedVcd $end
$timescale 1ps $end

 $scope module TOP $end
  $var wire  1 - areset_n $end
  $var wire  8 . datain [7:0] $end
  $var wire  1 4 empty $end
  $var wire  1 3 full $end
  $var wire  8 2 q [7:0] $end
  $var wire  1 0 rd_clk $end
  $var wire  1 1 read $end
  $var wire  1 , wr_clk $end
  $var wire  1 / write $end
  $scope module asynch_fifo $end
   $var wire 32 : AWIDTH [31:0] $end
   $var wire 32 9 DWIDTH [31:0] $end
   $var wire  1 - areset_n $end
   $var wire  1 7 areset_n_ms $end
   $var wire  1 8 areset_n_wr $end
   $var wire  8 & data_int [7:0] $end
   $var wire  8 . datain [7:0] $end
   $var wire  1 4 empty $end
   $var wire  1 3 full $end
   $var wire 32 ; i [31:0] $end
   $var wire  8 2 q [7:0] $end
   $var wire  1 0 rd_clk $end
   $var wire  1 1 read $end
   $var wire  6 5 rptr [5:0] $end
   $var wire  6 6 rptr_gray [5:0] $end
   $var wire  6 # rptr_ms [5:0] $end
   $var wire  6 $ rptr_wr [5:0] $end
   $var wire  7 % rptr_wr_bin [6:0] $end
   $var wire  6 ) wptr [5:0] $end
   $var wire  6 + wptr_gray [5:0] $end
   $var wire  6 ' wptr_ms [5:0] $end
   $var wire  7 * wptr_next [6:0] $end
   $var wire  6 ( wptr_rd [5:0] $end
   $var wire  1 , wr_clk $end
   $var wire  1 / write $end
   $scope module dp_dcram_0 $end
    $var wire 32 : AWIDTH [31:0] $end
    $var wire 32 9 DWIDTH [31:0] $end
    $var wire  6 ) addr0 [5:0] $end
    $var wire  6 5 addr1 [5:0] $end
    $var wire  8 . data0 [7:0] $end
    $var wire  8 & q1 [7:0] $end
    $var wire  1 0 rd_clk $end
    $var wire  1 1 re1 $end
    $var wire  1 / we0 $end
    $var wire  1 , wr_clk $end
   $upscope $end
  $upscope $end
 $upscope $end
$enddefinitions $end


#0
b000000 #
b000000 $
b0000000 %
b00000000 &
b000000 '
b000000 (
b000000 )
b0000001 *
b000000 +
1,
0-
b00000000 .
0/
10
01
b00000000 2
03
14
b000000 5
b000000 6
07
08
b00000000000000000000000000001000 9
b00000000000000000000000000000110 :
b00000000000000000000000000000110 ;
#1
#2
#3
#4
#5
#6
#7
#8
#9
#10
0,
#11
#12
00
#13
#14
#15
#16
#17
#18
#19
#20
1,
#21
#22
#23
#24
10
#25
#26
#27
#28
#29
#30
0,
#31
#32
#33
#34
#35
#36
00
#37
#38
#39
#40
1,
#41
#42
#43
#44
#45
#46
#47
#48
10
#49
#50
0,
#51
#52
#53
#54
#55
#56
#57
#58
#59
#60
1,
00
#61
#62
#63
#64
#65
#66
#67
#68
#69
#70
0,
#71
#72
10
#73
#74
#75
#76
#77
#78
#79
#80
1,
#81
#82
#83
#84
00
#85
#86
#87
#88
#89
#90
0,
#91
#92
#93
#94
#95
#96
10
#97
#98
#99
#100
1,
1-
17
#101
#102
#103
#104
#105
#106
#107
#108
00
#109
#110
0,
#111
#112
#113
#114
#115
#116
#117
#118
#119
#120
1,
10
18
#121
#122
#123
#124
#125
#126
#127
#128
#129
#130
0,
#131
#132
00
#133
#134
#135
#136
#137
#138
#139
#140
1,
#141
#142
#143
#144
10
#145
b00110001 .
1/
#146
#147
#148
#149
#150
0,
#151
#152
#153
#154
#155
#156
00
#157
#158
#159
#160
b000001 )
b0000010 *
b000001 +
1,
#161
#162
#163
#164
#165
0/
#166
#167
#168
b000001 '
10
#169
#170
0,
#171
#172
#173
#174
#175
#176
#177
#178
#179
#180
1,
00
#181
#182
#183
#184
#185
b00110010 .
1/
#186
#187
#188
#189
#190
0,
#191
#192
b000001 (
10
04
#193
#194
#195
#196
#197
#198
#199
#200
b000010 )
b0000011 *
b000011 +
1,
#201
#202
#203
#204
00
#205
0/
#206
#207
#208
#209
#210
0,
#211
#212
#213
#214
#215
#216
b000011 '
10
#217
#218
#219
#220
1,
#221
#222
#223
#224
#225
b00110011 .
1/
#226
#227
#228
00
#229
#230
0,
#231
#232
#233
#234
#235
#236
#237
#238
#239
#240
b000011 (
b000011 )
b0000100 *
b000010 +
1,
10
#241
#242
#243
#244
#245
0/
#246
#247
#248
#249
#250
0,
#251
#252
00
#253
#254
#255
#256
#257
#258
#259
#260
1,
#261
#262
#263
#264
b000010 '
10
#265
b00110100 .
1/
#266
#267
#268
#269
#270
0,
#271
#272
#273
#274
#275
#276
00
#277
#278
#279
#280
b000100 )
b0000101 *
b000110 +
1,
#281
#282
#283
#284
#285
0/
#286
#287
#288
b000110 '
b000010 (
10
#289
#290
0,
#291
#292
#293
#294
#295
#296
#297
#298
#299
#300
1,
00
#301
#302
#303
#304
#305
b00110101 .
1/
#306
#307
#308
#309
#310
0,
#311
#312
b000110 (
10
#313
#314
#315
#316
#317
#318
#319
#320
b000101 )
b0000110 *
b000111 +
1,
#321
#322
#323
#324
00
#325
0/
#326
#327
#328
#329
#330
0,
#331
#332
#333
#334
#335
#336
b000111 '
10
#337
#338
#339
#340
1,
#341
#342
#343
#344
#345
b00110110 .
1/
#346
#347
#348
00
#349
#350
0,
#351
#352
#353
#354
#355
#356
#357
#358
#359
#360
b000111 (
b000110 )
b0000111 *
b000101 +
1,
10
#361
#362
#363
#364
#365
0/
#366
#367
#368
#369
#370
0,
#371
#372
00
#373
#374
#375
#376
#377
#378
#379
#380
1,
#381
#382
#383
#384
b000101 '
10
#385
b00110111 .
1/
#386
#387
#388
#389
#390
0,
#391
#392
#393
#394
#395
#396
00
#397
#398
#399
#400
b000111 )
b0001000 *
b000100 +
1,
#401
#402
#403
#404
#405
0/
#406
#407
#408
b000100 '
b000101 (
10
#409
#410
0,
#411
#412
#413
#414
#415
#416
#417
#418
#419
#420
1,
00
#421
#422
#423
#424
#425
#426
#427
#428
#429
11
#430
0,
#431
#432
b00110001 &
b000100 (
10
b00110001 2
b000001 5
b000001 6
#433
#434
#435
#436
#437
#438
#439
#440
b000001 #
1,
#441
#442
#443
#444
00
#445
#446
#447
#448
#449
#450
0,
#451
#452
#453
01
#454
#455
#456
10
#457
#458
#459
#460
b000001 $
b0000001 %
1,
#461
#462
#463
#464
#465
#466
#467
#468
00
#469
#470
0,
#471
#472
#473
#474
#475
#476
#477
11
#478
#479
#480
b00110010 &
1,
10
b00110010 2
b000010 5
b000011 6
#481
#482
#483
#484
#485
#486
#487
#488
#489
#490
0,
#491
#492
00
#493
#494
#495
#496
#497
#498
#499
#500
b000011 #
1,
#501
01
#502
#503
#504
10
#505
#506
#507
#508
#509
#510
0,
#511
#512
#513
#514
#515
#516
00
#517
#518
#519
#520
b000011 $
b0000010 %
1,
#521
#522
#523
#524
#525
11
#526
#527
#528
b00110011 &
10
b00110011 2
b000011 5
b000010 6
#529
#530
0,
#531
#532
#533
#534
#535
#536
#537
#538
#539
#540
b000010 #
1,
00
#541
#542
#543
#544
#545
#546
#547
#548
#549
01
#550
0,
#551
#552
10
#553
#554
#555
#556
#557
#558
#559
#560
b000010 $
b0000011 %
1,
#561
#562
#563
#564
00
#565
#566
#567
#568
#569
#570
0,
#571
#572
#573
11
#574
#575
#576
b00110100 &
10
b00110100 2
b000100 5
b000110 6
#577
#578
#579
#580
b000110 #
1,
#581
#582
#583
#584
#585
#586
#587
#588
00
#589
#590
0,
#591
#592
#593
#594
#595
#596
#597
01
#598
#599
#600
b000110 $
b0000100 %
1,
10
#601
#602
#603
#604
#605
#606
#607
#608
#609
#610
0,
#611
#612
00
#613
#614
#615
#616
#617
#618
#619
#620
1,
#621
11
#622
#623
#624
b00110101 &
10
b00110101 2
b000101 5
b000111 6
#625
#626
#627
#628
#629
#630
0,
#631
#632
#633
#634
#635
#636
00
#637
#638
#639
#640
b000111 #
1,
#641
#642
#643
#644
#645
01
#646
#647
#648
10
#649
#650
0,
#651
#652
#653
#654
#655
#656
#657
#658
#659
#660
b000111 $
b0000101 %
1,
00
#661
#662
#663
#664
#665
#666
#667
#668
#669
11
#670
0,
#671
#672
b00110110 &
10
b00110110 2
b000110 5
b000101 6
#673
#674
#675
#676
#677
#678
#679
#680
b000101 #
1,
#681
#682
#683
#684
00
#685
#686
#687
#688
#689
#690
0,
#691
#692
#693
01
#694
#695
#696
10
#697
#698
#699
#700
b000101 $
b0000110 %
1,
#701
#702
#703
#704
#705
#706
#707
#708
00
#709
#710
0,
#711
#712
#713
#714
#715
#716
#717
11
#718
#719
#720
b00110111 &
1,
10
b00110111 2
14
b000111 5
b000100 6
#721
#722
#723
#724
#725
#726
#727
#728
#729
#730
0,
#731
#732
00
#733
#734
#735
#736
#737
#738
#739
#740
b000100 #
1,
#741
#742
#743
#744
b00000000 &
10
b00000000 2
04
b001000 5
b001100 6
#745
#746
#747
#748
#749
#750
0,
#751
#752
#753
#754
#755
#756
00
#757
#758
#759
#760
b001100 #
b000100 $
b0000111 %
1,
#761
#762
#763
#764
#765
#766
#767
#768
10
b001001 5
b001101 6
#769
#770
0,
#771
#772
#773
#774
#775
#776
#777
#778
#779
#780
b001101 #
b001100 $
b0001000 %
1,
00
13
#781
#782
#783
#784
#785
#786
#787
#788
#789
#790
0,
#791
#792
10
b001010 5
b001111 6
#793
#794
#795
#796
#797
#798
#799
#800
b001111 #
b001101 $
b0001001 %
1,
03
#801
#802
#803
#804
00
#805
#806
#807
#808
#809
#810
0,
#811
#812
#813
#814
#815
#816
10
b001011 5
b001110 6
#817
#818
#819
#820
b001110 #
b001111 $
b0001010 %
1,
#821
#822
#823
#824
#825
#826
#827
#828
00
#829
#830
0,
#831
#832
#833
#834
#835
#836
#837
#838
#839
#840
b001110 $
b0001011 %
1,
10
b001100 5
b001010 6
#841
#842
#843
#844
#845
#846
#847
#848
#849
#850
0,
#851
#852
00
#853
#854
#855
#856
#857
#858
#859
#860
b001010 #
1,
#861
#862
#863
#864
10
b001101 5
b001011 6
#865
#866
#867
#868
#869
#870
0,
#871
#872
#873
#874
#875
#876
00
#877
#878
#879
#880
b001011 #
b001010 $
b0001100 %
1,
#881
#882
#883
#884
#885
#886
#887
#888
10
b001110 5
b001001 6
#889
#890
0,
#891
#892
#893
#894
#895
#896
#897
#898
#899
#900
b001001 #
b001011 $
b0001101 %
1,
00
#901
#902
#903
#904
#905
#906
#907
#908
#909
#910
0,
#911
#912
10
b001111 5
b001000 6
#913
#914
#915
#916
#917
#918
#919
#920
b001000 #
b001001 $
b0001110 %
1,
#921
#922
#923
#924
00
#925
#926
#927
#928
#929
#930
0,
#931
#932
#933
#934
#935
#936
10
b010000 5
b011000 6
#937
#938
#939
#940
b011000 #
b001000 $
b0001111 %
1,
#941
#942
#943
#944
#945
#946
#947
#948
00
#949
#950
0,
#951
#952
#953
#954
#955
#956
#957
#958
#959
#960
b011000 $
b0010000 %
1,
10
b010001 5
b011001 6
#961
#962
#963
#964
#965
#966
#967
#968
#969
#970
0,
#971
#972
00
#973
#974
#975
#976
#977
#978
#979
#980
b011001 #
1,
#981
#982
#983
#984
10
b010010 5
b011011 6
